{"SubTexture":[{"width":27,"y":396,"height":22,"name":"黄彩带","x":462},{"width":34,"y":356,"height":38,"name":"蓝彩带","x":462},{"width":40,"y":506,"height":49,"name":"红彩带","x":462},{"frameX":-65,"frameHeight":279,"y":1,"frameY":-48,"frameWidth":720,"width":479,"height":215,"name":"光晕","x":1},{"width":16,"y":396,"height":17,"name":"粒子","x":491},{"width":46,"y":459,"height":32,"name":"右手","x":274},{"width":122,"y":599,"height":138,"name":"麻将人躯体","x":364},{"width":77,"y":459,"height":45,"name":"眼睛","x":390},{"width":19,"y":420,"height":26,"name":"嘴巴","x":462},{"width":56,"y":459,"height":25,"name":"左手","x":322},{"width":200,"y":218,"height":136,"name":"礼包","x":274},{"width":361,"y":599,"height":80,"name":"左彩带","x":1},{"width":387,"y":502,"height":95,"name":"标题版","x":1},{"width":187,"y":681,"height":54,"name":"迎新礼","x":1},{"width":186,"y":356,"height":101,"name":"标题发光 拷贝","x":274},{"width":59,"y":506,"height":20,"name":"眉毛","x":390},{"width":49,"y":557,"height":38,"name":"1","x":462},{"width":271,"y":218,"height":282,"name":"金光","x":1}],"width":513,"height":739,"name":"yingxinli-renwu","imagePath":"yingxinli-renwu_tex.png"}